{
  "to": "butterblume21397@gmx.de",
  "subject": "Schulprojekt: Website-Entwurf für Butterblume",
  "text": "Hallo,\n\nmein Name ist Levi, ich bin Schüler aus Lüneburg und mache ein Schulprojekt zum Thema Webdesign.\n\nIch hab mir Ihre Website angeschaut und einen modernen Entwurf gemacht:\n\nhttps://butterblume-barendorf.vercel.app\n\nDer Entwurf ist komplett unverbindlich - ich benötige praktische Erfahrung für mein Schulprojekt.\nFalls Ihnen die neue Webseite gefällt und Sie die Seite gerne haben möchten, melden Sie sich bitte bei mir!\nFür Sie fallen keine Kosten dafür an.\n\nViele Grüße\nLevi\nlevi.webdesign.lg@gmail.com",
  "lead": {
    "name": "Butterblume",
    "phone": "04137 7440",
    "email": "butterblume21397@gmx.de",
    "city": "Barendorf",
    "category": "florist",
    "website": "http://www.butterblume-barendorf.de/",
    "demoUrl": "https://butterblume-barendorf.vercel.app"
  },
  "createdAt": "2026-04-16T18:18:15.803Z",
  "sent": false
}